{
  "id": 1000,
  "name": "Distortus rex v3",
  "author": "Kai's workshop",
  "category": "Monsters",
  "description": "All rights of this mod belong to their respective owners. If you enjoy using our apps, kindly take a moment to rate them. Your feedback is highly appreciated and helps us improve our applications.",
  "downloadUrl": "https://raw.githubusercontent.com/Saykudan/iosmelonmods/refs/heads/main/Monsters/distortus_rex_v3/distortus_rex_v3.melmod",
  "dateAdded": "2026-03-01T22:41:08.900Z",
  "uploadedAt": "2026-03-22T21:24:04.244Z",
  "version": "1.0"
}